winrtocr/LICENSE
winrtocr/README.MD
winrtocr/__init__.py
winrtocr/call3.py
winrtocr/requirements.txt
winrtocr/thirdparty.json
winrtocr-0.10.dist-info/LICENSE.rst
winrtocr-0.10.dist-info/METADATA
winrtocr-0.10.dist-info/WHEEL
winrtocr-0.10.dist-info/top_level.txt
winrtocr-0.10.dist-info/RECORD
