Metadata-Version: 2.1
Name: winrtocr
Version: 0.10
Summary: Multiprocessing library for OCR with WinRT
Home-page: https://github.com/hansalemaos/winrtocr
Author: Johannes Fischer
Author-email: <aulasparticularesdealemaosp@gmail.com>
License: MIT
Keywords: Multiprocessing,WinRT,ocr,tesseract
Classifier: Development Status :: 4 - Beta
Classifier: Programming Language :: Python :: 3 :: Only
Classifier: Programming Language :: Python :: 3.10
Classifier: Topic :: Scientific/Engineering :: Visualization
Classifier: Topic :: Software Development :: Libraries :: Python Modules
Classifier: Topic :: Utilities
License-File: LICENSE.rst
Requires-Dist: a-cv-imwrite-imread-plus
Requires-Dist: callpyfile
Requires-Dist: flatten-everything
Requires-Dist: kthread-sleep
Requires-Dist: opencv-python
Requires-Dist: pandas
Requires-Dist: pathos
Requires-Dist: PrettyColorPrinter
Requires-Dist: winsdk
